LICENSE
MANIFEST.in
README.md
quicktest.py
settings_test.py
setup.py
django_m2m_history.egg-info/PKG-INFO
django_m2m_history.egg-info/SOURCES.txt
django_m2m_history.egg-info/dependency_links.txt
django_m2m_history.egg-info/not-zip-safe
django_m2m_history.egg-info/requires.txt
django_m2m_history.egg-info/top_level.txt
m2m_history/__init__.py
m2m_history/__init__.pyc
m2m_history/descriptors.py
m2m_history/descriptors.pyc
m2m_history/fields.py
m2m_history/fields.pyc
m2m_history/models.py
m2m_history/models.pyc
m2m_history/signals.py
m2m_history/signals.pyc
m2m_history/tests.py
m2m_history/tests.pyc
m2m_history/migrations/0001_initial.py
m2m_history/migrations/0001_initial.pyc
m2m_history/migrations/__init__.py
m2m_history/migrations/__init__.pyc